[
  {
    "question": "[File: 'File Name: rest/routes/accountRoute.js -> Scope: High: Authorizing transactions without approval from signers/owners'] [Function: getAccountCryptoAllowances()] Can an unprivileged external user call the /allowances/crypto endpoint for a victim account with a spender.id lte filter set to the maximum entity ID, causing extractCryptoAllowancesQuery() to return all authorized spenders up to that ID, effectively returning all allowances for the account without any restriction or owner approval?",
    "url": "https://deepwiki.com/search/-security-audit-prompt-securit_06d952d7-52c8-445e-b498-f32758d50b36?mode=deep",
    "timestamp": "2026-04-29 04:09:00.880865",
    "report_generated": false
  },
  {
    "question": "[File: 'File Name: rest/routes/accountRoute.js -> Scope: High: Authorizing transactions without approval from signers/owners'] [Function: getAccountTokenAllowances()] Can an unprivileged external user call the /allowances/tokens endpoint for a victim account with no filters, causing extractTokenMultiUnionQuery() to return all token allowances with default limit and order, and paginate through all results to build a complete map of the account's token authorization state without any owner approval or authentication?",
    "url": "https://deepwiki.com/search/-security-audit-prompt-securit_a9fb28df-5657-498f-852e-0a7e92fa6071?mode=deep",
    "timestamp": "2026-04-29 04:09:12.893507",
    "report_generated": false
  }
]